LICENSE
README.md
setup.py
metasequoia_java/__init__.py
metasequoia_java/entrance.py
metasequoia_java.egg-info/PKG-INFO
metasequoia_java.egg-info/SOURCES.txt
metasequoia_java.egg-info/dependency_links.txt
metasequoia_java.egg-info/top_level.txt
metasequoia_java/ast/__init__.py
metasequoia_java/ast/base.py
metasequoia_java/ast/constants.py
metasequoia_java/ast/dump.py
metasequoia_java/ast/element.py
metasequoia_java/ast/generate_utils.py
metasequoia_java/ast/info.py
metasequoia_java/ast/kind.py
metasequoia_java/ast/node.py
metasequoia_java/common/__init__.py
metasequoia_java/common/logger.py
metasequoia_java/grammar/__init__.py
metasequoia_java/grammar/parans_result.py
metasequoia_java/grammar/parser.py
metasequoia_java/grammar/parser_mode.py
metasequoia_java/grammar/token_set.py
metasequoia_java/grammar/grammar_enum/__init__.py
metasequoia_java/grammar/grammar_enum/enumerator_estimate.py
metasequoia_java/grammar/grammar_enum/operator_precedence.py
metasequoia_java/grammar/grammar_enum/pattern_result.py
metasequoia_java/grammar/grammar_hash/__init__.py
metasequoia_java/grammar/grammar_hash/assign_operator.py
metasequoia_java/grammar/grammar_hash/binary_operator.py
metasequoia_java/grammar/grammar_hash/modifier.py
metasequoia_java/grammar/grammar_hash/primitive_type.py
metasequoia_java/grammar/grammar_hash/token_precedence.py
metasequoia_java/grammar/grammar_hash/unary_operator.py
metasequoia_java/lexical/__init__.py
metasequoia_java/lexical/charset.py
metasequoia_java/lexical/keyword_hash.py
metasequoia_java/lexical/lexer.py
metasequoia_java/lexical/split_hash.py
metasequoia_java/lexical/state.py
metasequoia_java/lexical/token.py
metasequoia_java/lexical/token_kind.py
metasequoia_java/sa/__init__.py
metasequoia_java/sa/name_space.py
metasequoia_java/sa/constants/__init__.py
metasequoia_java/sa/constants/java_lang_class_name_set.py
metasequoia_java/sa/context/__init__.py
metasequoia_java/sa/context/base_context.py
metasequoia_java/sa/context/class_context.py
metasequoia_java/sa/context/file_context.py
metasequoia_java/sa/context/functions.py
metasequoia_java/sa/context/method_context.py
